annonition/__init__.py
annonition/logger.py
annonition/main.py
annonition-0.1.17.dist-info/LICENSE
annonition-0.1.17.dist-info/METADATA
annonition-0.1.17.dist-info/WHEEL
annonition-0.1.17.dist-info/top_level.txt
annonition-0.1.17.dist-info/RECORD
