Metadata-Version: 2.1
Name: annonition
Version: 0.1.17
Summary: Log everything in style.
Author: Abtin Turing
Classifier: Programming Language :: Python :: 3
Classifier: License :: OSI Approved :: MIT License
Classifier: Operating System :: OS Independent
License-File: LICENSE
Requires-Dist: coloredlogs
Requires-Dist: verboselogs
Requires-Dist: yaspin
